typed_htx/__init__.py
typed_htx-0.1.0.dist-info/METADATA
typed_htx-0.1.0.dist-info/WHEEL
typed_htx-0.1.0.dist-info/top_level.txt
typed_htx-0.1.0.dist-info/RECORD
