Metadata-Version: 2.4
Name: typed-htx
Version: 0.1.0
Summary: A fully typed, validated async client for the Htx API
Author-email: Marcel Claramunt <marcel@tribulnation.com>
Project-URL: repo, https://github.com/tribulnation/REPO.git
Requires-Python: >=3.10
